<?xml version="1.0" encoding="UTF-8" ?>
<ModMetaData>
	<name>Snap Out! - Türkçe Çeviri</name>
	<author>Hamza YILMAZ</author>
    <supportedVersions>
		<li>1.5</li>
	</supportedVersions>
		<modDependencies>		
		<li>
			<packageId>weilbyte.snapout</packageId>
			<displayName>Snap Out!</displayName>
			<steamWorkshopUrl>steam://url/CommunityFilePage/1319782555</steamWorkshopUrl>
		</li>		
	</modDependencies>
		<loadAfter>
		<li>weilbyte.snapout</li>
	</loadAfter>
	<packageId>hyilmaz.rimword.tr.1319782555</packageId>
	<description>	
Hakkında:

Snap Out! modunun Türkçe çevirisi.
Bazı çeviri hataları olabilir. 
Bu modların Türkçe çevirileri olmadığından kendi oyunum için çevirdim ve paylaşmaya karar verdim.
Bi nebze de olsa belki işinize yarayabilir.

https://github.com/radiatez/Rimword_Turkish_Translate

Hamza YILMAZ	
	</description>
</ModMetaData>

